matchgrowth/__init__.py
matchgrowth-0.0.9.data/scripts/match-growth.py
matchgrowth-0.0.9.dist-info/LICENSE
matchgrowth-0.0.9.dist-info/METADATA
matchgrowth-0.0.9.dist-info/WHEEL
matchgrowth-0.0.9.dist-info/top_level.txt
matchgrowth-0.0.9.dist-info/RECORD
