Metadata-Version: 2.1
Name: matchgrowth
Version: 0.0.9
Summary: Tool for estimating growth rates
Home-page: https://blog.garage-coding.com/
Author: Stefan Corneliu Petrea
Author-email: stefan@garage-coding.com
License: UNKNOWN
Platform: UNKNOWN
Classifier: Programming Language :: Python :: 3
Classifier: License :: OSI Approved :: MIT License
Classifier: Operating System :: OS Independent
Requires-Python: >=3.5
Requires-Dist: matplotlib (>=3.3.3)
Requires-Dist: numpy (>=1.19.4)
Requires-Dist: scipy (>=1.5.4)
Requires-Dist: similaritymeasures (>=0.4.4)
Requires-Dist: sympy (>=1.7.1)
